hone/__init__.py
hone/__main__.py
hone/hone.py
hone/test/__init__.py
hone/test/test_csv_utils.py
hone/test/test_hone.py
hone/utils/__init__.py
hone/utils/csv_utils.py
hone/utils/json_utils.py
hone/utils/test_utils.py
hone-0.2.1.dist-info/LICENSE
hone-0.2.1.dist-info/METADATA
hone-0.2.1.dist-info/WHEEL
hone-0.2.1.dist-info/entry_points.txt
hone-0.2.1.dist-info/top_level.txt
hone-0.2.1.dist-info/RECORD
